{
  "_id": 30034944,
  "_isComplete": true,
  "__v": 24060,
  "_lastUpdate": "2017-02-17T08:04:12.384Z",
  "appealsEndDate": "2013-07-27T18:05:00.000Z",
  "challengeCommunity": "develop",
  "challengeName": "Proof of Concept Assembly - CSFV Chat Module Clustering",
  "challengeType": "Assembly Competition",
  "checkpointSubmissionEndDate": null,
  "currentPhaseEndDate": null,
  "currentPhaseName": "Stalled",
  "currentPhaseRemainingTime": 0,
  "currentStatus": "Cancelled - Zero Submissions",
  "detailedRequirements": "<p><a href=\"http://apps.topcoder.com/wiki/display/docs/Proof+of+Concept+Assembly+-+CSFV+Chat+Module+Clustering\">http://apps.topcoder.com/wiki/display/docs/Proof+of+Concept+Assembly+-+CSFV+Chat+Module+Clustering</a></p>\n",
  "digitalRunPoints": 450,
  "directUrl": "https://www.topcoder.com/direct/contest/detail.action?projectId=30034944",
  "finalFixEndDate": "2013-07-29T00:05:00.000Z",
  "finalSubmissionGuidelines": "<p><a href=\"http://apps.topcoder.com/wiki/display/docs/Proof+of+Concept+Assembly+-+CSFV+Chat+Module+Clustering\">http://apps.topcoder.com/wiki/display/docs/Proof+of+Concept+Assembly+-+CSFV+Chat+Module+Clustering</a></p>\n",
  "forumId": 18501,
  "forumLink": "http://apps.topcoder.com/forums/?module=Category&categoryID=18501",
  "numberOfCheckpointSubmissions": 0,
  "numberOfCheckpointsPrizes": 0,
  "numberOfRegistrants": 15,
  "numberOfSubmissions": 0,
  "postingDate": "2013-07-21T12:00:00.000Z",
  "projectId": 6433,
  "registrationEndDate": "2013-07-23T12:00:00.000Z",
  "reliabilityBonus": 200,
  "reviewScorecardId": 30001210,
  "reviewType": null,
  "screeningScorecardId": 30000412,
  "submissionEndDate": "2013-07-25T12:05:00.000Z",
  "submissions": [],
  "phases": [
    {
      "type": "Specification Submission",
      "status": "Closed",
      "scheduledStartTime": "2013-07-20T17:57:00.000Z",
      "actualStartTime": "2013-07-20T17:57:00.000Z",
      "scheduledEndTime": "2013-07-20T17:58:00.000Z",
      "actualendTime": "2013-07-20T17:58:00.000Z",
      "_id": "58a6ae7c5d036c0bbdd5ddb3"
    },
    {
      "type": "Specification Review",
      "status": "Closed",
      "scheduledStartTime": "2013-07-20T17:58:00.000Z",
      "actualStartTime": "2013-07-20T17:58:00.000Z",
      "scheduledEndTime": "2013-07-21T01:48:00.000Z",
      "actualendTime": "2013-07-21T01:48:00.000Z",
      "_id": "58a6ae7c5d036c0bbdd5ddb2"
    },
    {
      "type": "Registration",
      "status": "Closed",
      "scheduledStartTime": "2013-07-21T12:00:00.000Z",
      "actualStartTime": "2013-07-21T12:00:00.000Z",
      "scheduledEndTime": "2013-07-23T12:00:00.000Z",
      "actualendTime": "2013-07-23T12:00:00.000Z",
      "_id": "58a6ae7c5d036c0bbdd5ddb1"
    },
    {
      "type": "Submission",
      "status": "Closed",
      "scheduledStartTime": "2013-07-21T12:05:00.000Z",
      "actualStartTime": "2013-07-21T12:05:00.000Z",
      "scheduledEndTime": "2013-07-25T12:05:00.000Z",
      "actualendTime": "2013-07-25T12:05:00.000Z",
      "_id": "58a6ae7c5d036c0bbdd5ddb0"
    },
    {
      "type": "Screening",
      "status": "Scheduled",
      "scheduledStartTime": "2013-07-25T12:05:00.000Z",
      "actualStartTime": null,
      "scheduledEndTime": "2013-07-26T00:05:00.000Z",
      "actualendTime": null,
      "_id": "58a6ae7c5d036c0bbdd5ddaf"
    },
    {
      "type": "Review",
      "status": "Scheduled",
      "scheduledStartTime": "2013-07-26T00:05:00.000Z",
      "actualStartTime": null,
      "scheduledEndTime": "2013-07-27T00:05:00.000Z",
      "actualendTime": null,
      "_id": "58a6ae7c5d036c0bbdd5ddae"
    },
    {
      "type": "Appeals",
      "status": "Scheduled",
      "scheduledStartTime": "2013-07-27T00:05:00.000Z",
      "actualStartTime": null,
      "scheduledEndTime": "2013-07-27T12:05:00.000Z",
      "actualendTime": null,
      "_id": "58a6ae7c5d036c0bbdd5ddad"
    },
    {
      "type": "Appeals Response",
      "status": "Scheduled",
      "scheduledStartTime": "2013-07-27T12:05:00.000Z",
      "actualStartTime": null,
      "scheduledEndTime": "2013-07-27T18:05:00.000Z",
      "actualendTime": null,
      "_id": "58a6ae7c5d036c0bbdd5ddac"
    },
    {
      "type": "Aggregation",
      "status": "Scheduled",
      "scheduledStartTime": "2013-07-27T18:05:00.000Z",
      "actualStartTime": null,
      "scheduledEndTime": "2013-07-28T00:05:00.000Z",
      "actualendTime": null,
      "_id": "58a6ae7c5d036c0bbdd5ddab"
    },
    {
      "type": "Final Fix",
      "status": "Scheduled",
      "scheduledStartTime": "2013-07-28T00:05:00.000Z",
      "actualStartTime": null,
      "scheduledEndTime": "2013-07-29T00:05:00.000Z",
      "actualendTime": null,
      "_id": "58a6ae7c5d036c0bbdd5ddaa"
    },
    {
      "type": "Final Review",
      "status": "Scheduled",
      "scheduledStartTime": "2013-07-29T00:05:00.000Z",
      "actualStartTime": null,
      "scheduledEndTime": "2013-07-29T12:05:00.000Z",
      "actualendTime": null,
      "_id": "58a6ae7c5d036c0bbdd5dda9"
    },
    {
      "type": "Approval",
      "status": "Scheduled",
      "scheduledStartTime": "2013-07-29T12:05:00.000Z",
      "actualStartTime": null,
      "scheduledEndTime": "2013-08-03T12:05:00.000Z",
      "actualendTime": null,
      "_id": "58a6ae7c5d036c0bbdd5dda8"
    },
    {
      "type": "Post-Mortem",
      "status": "Closed",
      "scheduledStartTime": "2013-07-25T12:06:00.000Z",
      "actualStartTime": "2013-07-25T12:06:00.000Z",
      "scheduledEndTime": "2013-08-03T14:05:00.000Z",
      "actualendTime": "2013-08-03T14:05:00.000Z",
      "_id": "58a6ae7c5d036c0bbdd5dda7"
    }
  ],
  "registrants": [
    {
      "handle": "woodjhon",
      "reliability": "n/a",
      "registrationDate": "2013-07-21T12:09:00.000Z",
      "submissionDate": null,
      "rating": null,
      "colorStyle": "color: #000000",
      "_id": "58a6ae7c5d036c0bbdd5dda6"
    },
    {
      "handle": "ramakrishnaxii",
      "reliability": "n/a",
      "registrationDate": "2013-07-21T13:36:00.000Z",
      "submissionDate": null,
      "rating": null,
      "colorStyle": "color: #000000",
      "_id": "58a6ae7c5d036c0bbdd5dda5"
    },
    {
      "handle": "Schpotsky",
      "reliability": "n/a",
      "registrationDate": "2013-07-21T13:54:00.000Z",
      "submissionDate": null,
      "rating": null,
      "colorStyle": "color: #000000",
      "_id": "58a6ae7c5d036c0bbdd5dda4"
    },
    {
      "handle": "Luca",
      "reliability": "0%",
      "registrationDate": "2013-07-21T14:13:00.000Z",
      "submissionDate": null,
      "rating": "1423",
      "colorStyle": "color: #6666FF",
      "_id": "58a6ae7c5d036c0bbdd5dda3"
    },
    {
      "handle": "agus.mw",
      "reliability": "n/a",
      "registrationDate": "2013-07-21T14:36:00.000Z",
      "submissionDate": null,
      "rating": null,
      "colorStyle": "color: #000000",
      "_id": "58a6ae7c5d036c0bbdd5dda2"
    },
    {
      "handle": "pfilippi",
      "reliability": "0%",
      "registrationDate": "2013-07-21T17:07:00.000Z",
      "submissionDate": null,
      "rating": "889",
      "colorStyle": "color: #999999",
      "_id": "58a6ae7c5d036c0bbdd5dda1"
    },
    {
      "handle": "akhil_bansal",
      "reliability": "n/a",
      "registrationDate": "2013-07-21T19:11:00.000Z",
      "submissionDate": null,
      "rating": null,
      "colorStyle": "color: #000000",
      "_id": "58a6ae7c5d036c0bbdd5dda0"
    },
    {
      "handle": "yedtoss",
      "reliability": "n/a",
      "registrationDate": "2013-07-21T23:18:00.000Z",
      "submissionDate": null,
      "rating": null,
      "colorStyle": "color: #000000",
      "_id": "58a6ae7c5d036c0bbdd5dd9f"
    },
    {
      "handle": "muzehyun",
      "reliability": "6%",
      "registrationDate": "2013-07-22T00:42:00.000Z",
      "submissionDate": null,
      "rating": "761",
      "colorStyle": "color: #999999",
      "_id": "58a6ae7c5d036c0bbdd5dd9e"
    },
    {
      "handle": "alfiya_Zi",
      "reliability": "n/a",
      "registrationDate": "2013-07-22T05:04:00.000Z",
      "submissionDate": null,
      "rating": null,
      "colorStyle": "color: #000000",
      "_id": "58a6ae7c5d036c0bbdd5dd9d"
    },
    {
      "handle": "selvaa89",
      "reliability": "0%",
      "registrationDate": "2013-07-22T18:09:00.000Z",
      "submissionDate": null,
      "rating": "1123",
      "colorStyle": "color: #00A900",
      "_id": "58a6ae7c5d036c0bbdd5dd9c"
    },
    {
      "handle": "thientri",
      "reliability": "n/a",
      "registrationDate": "2013-07-22T22:29:00.000Z",
      "submissionDate": null,
      "rating": null,
      "colorStyle": "color: #000000",
      "_id": "58a6ae7c5d036c0bbdd5dd9b"
    },
    {
      "handle": "ohyan07",
      "reliability": "n/a",
      "registrationDate": "2013-07-23T03:28:00.000Z",
      "submissionDate": null,
      "rating": null,
      "colorStyle": "color: #000000",
      "_id": "58a6ae7c5d036c0bbdd5dd9a"
    },
    {
      "handle": "sunbinbrother",
      "reliability": "n/a",
      "registrationDate": "2013-07-22T02:03:00.000Z",
      "submissionDate": null,
      "rating": null,
      "colorStyle": "color: #000000",
      "_id": "58a6ae7c5d036c0bbdd5dd99"
    },
    {
      "handle": "Sky_",
      "reliability": "60%",
      "registrationDate": "2013-07-22T10:37:00.000Z",
      "submissionDate": null,
      "rating": "910",
      "colorStyle": "color: #00A900",
      "_id": "58a6ae7c5d036c0bbdd5dd98"
    }
  ],
  "event": {
    "id": 3437,
    "description": "2014 TopCoder(R) Open",
    "shortDescription": "tco14"
  },
  "prize": [
    1000,
    500
  ],
  "technology": [
    "JavaScript",
    "Other"
  ],
  "platforms": []
}