{
  "_id": 30031576,
  "_isComplete": true,
  "__v": 1,
  "_lastUpdate": "2016-11-30T08:34:30.207Z",
  "appealsEndDate": "2013-01-08T09:06:00.000Z",
  "challengeCommunity": "develop",
  "challengeName": "System Assembly - FMS Report Integration",
  "challengeType": "Assembly Competition",
  "checkpointSubmissionEndDate": null,
  "currentPhaseEndDate": null,
  "currentPhaseName": "Stalled",
  "currentPhaseRemainingTime": 0,
  "currentStatus": "Completed",
  "detailedRequirements": "<p><a href=\"http://apps.topcoder.com/wiki/display/docs/System+Assembly+-+FMS+Report+Integration\" target=\"_blank\">http://apps.topcoder.com/wiki/display/docs/System+Assembly+-+FMS+Report+Integration</a></p>",
  "digitalRunPoints": 450,
  "directUrl": "https://www.topcoder.com/direct/contest/detail.action?projectId=30031576",
  "event": {
    "id": 3436,
    "description": "2013 TopCoder(R) Open",
    "shortDescription": "tco13"
  },
  "finalFixEndDate": "2013-01-21T03:46:00.000Z",
  "finalSubmissionGuidelines": "<p>N/A</p>",
  "forumId": 16371,
  "forumLink": "http://apps.topcoder.com/forums/?module=Category&categoryID=16371",
  "numberOfCheckpointSubmissions": 0,
  "numberOfCheckpointsPrizes": 0,
  "numberOfRegistrants": 13,
  "numberOfSubmissions": 1,
  "phases": [
    {
      "type": "Specification Submission",
      "status": "Closed",
      "scheduledStartTime": "2012-12-31T07:45:00.000Z",
      "actualStartTime": "2012-12-31T07:45:00.000Z",
      "scheduledEndTime": "2012-12-31T07:46:00.000Z",
      "actualendTime": "2012-12-31T07:46:00.000Z",
      "_id": "583e8f1610a1db09a46bef8a"
    },
    {
      "type": "Specification Review",
      "status": "Closed",
      "scheduledStartTime": "2012-12-31T07:46:00.000Z",
      "actualStartTime": "2012-12-31T07:46:00.000Z",
      "scheduledEndTime": "2012-12-31T14:11:00.000Z",
      "actualendTime": "2012-12-31T14:11:00.000Z",
      "_id": "583e8f1610a1db09a46bef89"
    },
    {
      "type": "Registration",
      "status": "Closed",
      "scheduledStartTime": "2012-12-31T15:44:00.000Z",
      "actualStartTime": "2012-12-31T15:44:00.000Z",
      "scheduledEndTime": "2013-01-02T15:44:00.000Z",
      "actualendTime": "2013-01-02T15:44:00.000Z",
      "_id": "583e8f1610a1db09a46bef88"
    },
    {
      "type": "Submission",
      "status": "Closed",
      "scheduledStartTime": "2012-12-31T15:49:00.000Z",
      "actualStartTime": "2012-12-31T15:49:00.000Z",
      "scheduledEndTime": "2013-01-05T15:49:00.000Z",
      "actualendTime": "2013-01-05T15:49:00.000Z",
      "_id": "583e8f1610a1db09a46bef87"
    },
    {
      "type": "Screening",
      "status": "Closed",
      "scheduledStartTime": "2013-01-05T15:49:00.000Z",
      "actualStartTime": "2013-01-05T15:49:00.000Z",
      "scheduledEndTime": "2013-01-06T02:30:00.000Z",
      "actualendTime": "2013-01-06T02:30:00.000Z",
      "_id": "583e8f1610a1db09a46bef86"
    },
    {
      "type": "Review",
      "status": "Closed",
      "scheduledStartTime": "2013-01-06T02:30:00.000Z",
      "actualStartTime": "2013-01-06T02:30:00.000Z",
      "scheduledEndTime": "2013-01-07T07:18:00.000Z",
      "actualendTime": "2013-01-07T07:18:00.000Z",
      "_id": "583e8f1610a1db09a46bef85"
    },
    {
      "type": "Appeals",
      "status": "Closed",
      "scheduledStartTime": "2013-01-07T07:18:00.000Z",
      "actualStartTime": "2013-01-07T07:18:00.000Z",
      "scheduledEndTime": "2013-01-08T07:18:00.000Z",
      "actualendTime": "2013-01-08T07:18:00.000Z",
      "_id": "583e8f1610a1db09a46bef84"
    },
    {
      "type": "Appeals Response",
      "status": "Closed",
      "scheduledStartTime": "2013-01-08T07:18:00.000Z",
      "actualStartTime": "2013-01-08T07:18:00.000Z",
      "scheduledEndTime": "2013-01-08T09:06:00.000Z",
      "actualendTime": "2013-01-08T09:06:00.000Z",
      "_id": "583e8f1610a1db09a46bef83"
    },
    {
      "type": "Aggregation",
      "status": "Closed",
      "scheduledStartTime": "2013-01-08T09:06:00.000Z",
      "actualStartTime": "2013-01-08T09:06:00.000Z",
      "scheduledEndTime": "2013-01-08T12:03:00.000Z",
      "actualendTime": "2013-01-08T12:03:00.000Z",
      "_id": "583e8f1610a1db09a46bef82"
    },
    {
      "type": "Final Fix",
      "status": "Closed",
      "scheduledStartTime": "2013-01-08T12:03:00.000Z",
      "actualStartTime": "2013-01-08T12:03:00.000Z",
      "scheduledEndTime": "2013-01-09T12:03:00.000Z",
      "actualendTime": "2013-01-09T12:03:00.000Z",
      "_id": "583e8f1610a1db09a46bef81"
    },
    {
      "type": "Final Review",
      "status": "Closed",
      "scheduledStartTime": "2013-01-09T12:03:00.000Z",
      "actualStartTime": "2013-01-09T12:03:00.000Z",
      "scheduledEndTime": "2013-01-09T14:39:00.000Z",
      "actualendTime": "2013-01-09T14:39:00.000Z",
      "_id": "583e8f1610a1db09a46bef80"
    },
    {
      "type": "Approval",
      "status": "Closed",
      "scheduledStartTime": "2013-01-10T08:36:00.000Z",
      "actualStartTime": "2013-01-10T08:36:00.000Z",
      "scheduledEndTime": "2013-01-15T03:38:00.000Z",
      "actualendTime": "2013-01-15T03:38:00.000Z",
      "_id": "583e8f1610a1db09a46bef7f"
    },
    {
      "type": "Specification Submission",
      "status": "Closed",
      "scheduledStartTime": "2012-12-31T14:11:00.000Z",
      "actualStartTime": "2012-12-31T14:11:00.000Z",
      "scheduledEndTime": "2012-12-31T15:03:00.000Z",
      "actualendTime": "2012-12-31T15:03:00.000Z",
      "_id": "583e8f1610a1db09a46bef7e"
    },
    {
      "type": "Specification Review",
      "status": "Closed",
      "scheduledStartTime": "2012-12-31T15:03:00.000Z",
      "actualStartTime": "2012-12-31T15:03:00.000Z",
      "scheduledEndTime": "2012-12-31T15:44:00.000Z",
      "actualendTime": "2012-12-31T15:44:00.000Z",
      "_id": "583e8f1610a1db09a46bef7d"
    },
    {
      "type": "Final Fix",
      "status": "Closed",
      "scheduledStartTime": "2013-01-09T14:39:00.000Z",
      "actualStartTime": "2013-01-09T14:39:00.000Z",
      "scheduledEndTime": "2013-01-10T05:33:00.000Z",
      "actualendTime": "2013-01-10T05:33:00.000Z",
      "_id": "583e8f1610a1db09a46bef7c"
    },
    {
      "type": "Final Review",
      "status": "Closed",
      "scheduledStartTime": "2013-01-10T05:33:00.000Z",
      "actualStartTime": "2013-01-10T05:33:00.000Z",
      "scheduledEndTime": "2013-01-10T08:35:00.000Z",
      "actualendTime": "2013-01-10T08:35:00.000Z",
      "_id": "583e8f1610a1db09a46bef7b"
    },
    {
      "type": "Final Fix",
      "status": "Closed",
      "scheduledStartTime": "2013-01-15T03:39:00.000Z",
      "actualStartTime": "2013-01-15T03:39:00.000Z",
      "scheduledEndTime": "2013-01-21T03:46:00.000Z",
      "actualendTime": "2013-01-21T03:46:00.000Z",
      "_id": "583e8f1610a1db09a46bef7a"
    },
    {
      "type": "Final Review",
      "status": "Closed",
      "scheduledStartTime": "2013-01-21T03:46:00.000Z",
      "actualStartTime": "2013-01-21T03:46:00.000Z",
      "scheduledEndTime": "2013-01-21T04:06:00.000Z",
      "actualendTime": "2013-01-21T04:06:00.000Z",
      "_id": "583e8f1610a1db09a46bef79"
    },
    {
      "type": "Approval",
      "status": "Closed",
      "scheduledStartTime": "2013-01-21T04:06:00.000Z",
      "actualStartTime": "2013-01-21T04:06:00.000Z",
      "scheduledEndTime": "2013-01-26T04:06:00.000Z",
      "actualendTime": "2013-01-26T04:06:00.000Z",
      "_id": "583e8f1610a1db09a46bef78"
    }
  ],
  "platforms": [],
  "postingDate": "2012-12-31T15:44:00.000Z",
  "prize": [
    1000,
    500
  ],
  "projectId": 4404,
  "registrants": [
    {
      "handle": "fabrizyo",
      "reliability": "0%",
      "registrationDate": "2012-12-31T16:12:00.000Z",
      "submissionDate": null,
      "rating": null,
      "colorStyle": "color: #000000",
      "_id": "583e8f1610a1db09a46bef77"
    },
    {
      "handle": "flytoj2ee",
      "reliability": "40%",
      "registrationDate": "2012-12-31T16:13:00.000Z",
      "submissionDate": "2013-01-05T06:48:00.000Z",
      "rating": "1257",
      "colorStyle": "color: #6666FF",
      "_id": "583e8f1610a1db09a46bef76"
    },
    {
      "handle": "padegal12",
      "reliability": "0%",
      "registrationDate": "2012-12-31T18:22:00.000Z",
      "submissionDate": null,
      "rating": "824",
      "colorStyle": "color: #999999",
      "_id": "583e8f1610a1db09a46bef75"
    },
    {
      "handle": "Schpotsky",
      "reliability": "n/a",
      "registrationDate": "2012-12-31T17:49:00.000Z",
      "submissionDate": null,
      "rating": null,
      "colorStyle": "color: #000000",
      "_id": "583e8f1610a1db09a46bef74"
    },
    {
      "handle": "luckvin",
      "reliability": "n/a",
      "registrationDate": "2012-12-31T19:26:00.000Z",
      "submissionDate": null,
      "rating": null,
      "colorStyle": "color: #000000",
      "_id": "583e8f1610a1db09a46bef73"
    },
    {
      "handle": "vokie",
      "reliability": "n/a",
      "registrationDate": "2012-12-31T20:06:00.000Z",
      "submissionDate": null,
      "rating": null,
      "colorStyle": "color: #000000",
      "_id": "583e8f1610a1db09a46bef72"
    },
    {
      "handle": "coderwong",
      "reliability": "20%",
      "registrationDate": "2013-01-01T04:16:00.000Z",
      "submissionDate": null,
      "rating": "1269",
      "colorStyle": "color: #6666FF",
      "_id": "583e8f1610a1db09a46bef71"
    },
    {
      "handle": "amanforindia",
      "reliability": "50%",
      "registrationDate": "2013-01-01T04:45:00.000Z",
      "submissionDate": null,
      "rating": "717",
      "colorStyle": "color: #999999",
      "_id": "583e8f1610a1db09a46bef70"
    },
    {
      "handle": "gjw99",
      "reliability": "6%",
      "registrationDate": "2013-01-01T06:25:00.000Z",
      "submissionDate": null,
      "rating": "1205",
      "colorStyle": "color: #6666FF",
      "_id": "583e8f1610a1db09a46bef6f"
    },
    {
      "handle": "woodjhon",
      "reliability": "n/a",
      "registrationDate": "2013-01-01T13:27:00.000Z",
      "submissionDate": null,
      "rating": null,
      "colorStyle": "color: #000000",
      "_id": "583e8f1610a1db09a46bef6e"
    },
    {
      "handle": "an_ant",
      "reliability": "25%",
      "registrationDate": "2013-01-02T01:07:00.000Z",
      "submissionDate": null,
      "rating": null,
      "colorStyle": "color: #000000",
      "_id": "583e8f1610a1db09a46bef6d"
    },
    {
      "handle": "poundinc_tc",
      "reliability": "n/a",
      "registrationDate": "2013-01-02T10:24:00.000Z",
      "submissionDate": null,
      "rating": "323",
      "colorStyle": "color: #999999",
      "_id": "583e8f1610a1db09a46bef6c"
    },
    {
      "handle": "fivestarwy",
      "reliability": "6%",
      "registrationDate": "2012-12-31T16:21:00.000Z",
      "submissionDate": null,
      "rating": "806",
      "colorStyle": "color: #999999",
      "_id": "583e8f1610a1db09a46bef6b"
    }
  ],
  "registrationEndDate": "2013-01-02T15:44:00.000Z",
  "reliabilityBonus": 200,
  "reviewScorecardId": 30001210,
  "reviewType": null,
  "screeningScorecardId": 30000412,
  "submissionEndDate": "2013-01-05T15:49:00.000Z",
  "submissions": [
    {
      "handle": "flytoj2ee",
      "placement": 1,
      "screeningScore": 100,
      "initialScore": 90.31,
      "finalScore": 91.61,
      "points": 450,
      "submissionStatus": "Active",
      "submissionDate": "2013-01-05T06:48:00.000Z",
      "_id": "583e8f1610a1db09a46bef8b"
    }
  ],
  "technology": [
    "Java"
  ]
}