{
  "_id": 30056194,
  "_isComplete": true,
  "__v": 36,
  "_lastUpdate": "2017-01-19T01:07:04.113Z",
  "appealsEndDate": "2017-01-18T21:12:00.000Z",
  "challengeCommunity": "develop",
  "challengeName": "SpaceNet Challenge - 5th Place",
  "challengeType": "First2Finish",
  "checkpointSubmissionEndDate": null,
  "currentPhaseEndDate": null,
  "currentPhaseName": "Stalled",
  "currentPhaseRemainingTime": 0,
  "currentStatus": "Completed",
  "detailedRequirements": "SpaceNet Challenge - 5th Place",
  "digitalRunPoints": null,
  "directUrl": "https://www.topcoder.com/direct/contest/detail.action?projectId=30056194",
  "finalSubmissionGuidelines": "SpaceNet Challenge - 5th Place",
  "forumId": 34925,
  "forumLink": "http://apps.topcoder.com/forums/?module=Category&categoryID=34925",
  "numberOfCheckpointSubmissions": 0,
  "numberOfCheckpointsPrizes": 0,
  "numberOfRegistrants": 1,
  "numberOfSubmissions": 1,
  "phases": [
    {
      "type": "Registration",
      "status": "Closed",
      "scheduledStartTime": "2017-01-19T14:00:00.000Z",
      "actualStartTime": "2017-01-18T21:07:00.000Z",
      "scheduledEndTime": "2017-02-18T14:00:00.000Z",
      "actualendTime": "2017-01-18T21:12:00.000Z",
      "_id": "5880113890ca64469c8fa0f5"
    },
    {
      "type": "Iterative Review",
      "status": "Closed",
      "scheduledStartTime": "2017-01-19T14:05:00.000Z",
      "actualStartTime": "2017-01-18T21:07:00.000Z",
      "scheduledEndTime": "2017-01-20T14:05:00.000Z",
      "actualendTime": "2017-01-18T21:12:00.000Z",
      "_id": "5880113890ca64469c8fa0f4"
    },
    {
      "type": "Submission",
      "status": "Closed",
      "scheduledStartTime": "2017-01-19T14:05:00.000Z",
      "actualStartTime": "2017-01-18T21:07:00.000Z",
      "scheduledEndTime": "2017-02-18T14:05:00.000Z",
      "actualendTime": "2017-01-18T21:12:00.000Z",
      "_id": "5880113890ca64469c8fa0f3"
    }
  ],
  "platforms": [
    "Other"
  ],
  "postingDate": "2017-01-18T21:07:00.000Z",
  "prize": [
    4500
  ],
  "projectId": 11391,
  "registrants": [
    {
      "handle": "bic-user",
      "reliability": "n/a",
      "registrationDate": "2017-01-18T20:51:00.000Z",
      "submissionDate": "2017-01-18T21:12:00.000Z",
      "rating": null,
      "colorStyle": "color: #000000",
      "_id": "5880113890ca64469c8fa0f2"
    }
  ],
  "registrationEndDate": "2017-01-18T21:12:00.000Z",
  "reviewScorecardId": 30001600,
  "reviewType": "INTERNAL",
  "screeningScorecardId": null,
  "submissionEndDate": "2017-01-18T21:12:00.000Z",
  "submissions": [
    {
      "handle": "bic-user",
      "placement": null,
      "screeningScore": null,
      "initialScore": 100,
      "finalScore": 100,
      "points": 0,
      "submissionStatus": "Active",
      "submissionDate": "2017-01-18T21:12:00.000Z",
      "_id": "5880113890ca64469c8fa0f6"
    }
  ],
  "technology": [
    "Other"
  ]
}